{
  "standings": [
    {"position":1,"team":{"name":"Arsenal","crestUrl":"https://crests.football-data.org/57.png"},"playedGames":38,"won":28,"draw":6,"lost":4,"goalsFor":85,"goalsAgainst":36,"goalDifference":49,"points":90,"form":"WWWDW"},
    {"position":2,"team":{"name":"Manchester City","crestUrl":"https://crests.football-data.org/65.png"},"playedGames":38,"won":27,"draw":5,"lost":6,"goalsFor":89,"goalsAgainst":35,"goalDifference":54,"points":86,"form":"WWLWD"},
    {"position":3,"team":{"name":"Manchester United","crestUrl":"https://crests.football-data.org/66.png"},"playedGames":38,"won":25,"draw":9,"lost":4,"goalsFor":70,"goalsAgainst":30,"goalDifference":40,"points":84,"form":"WDWLW"},
    {"position":4,"team":{"name":"Newcastle United","crestUrl":"https://crests.football-data.org/67.png"},"playedGames":38,"won":21,"draw":11,"lost":6,"goalsFor":68,"goalsAgainst":36,"goalDifference":32,"points":74,"form":"WWDWL"},
    {"position":5,"team":{"name":"Liverpool","crestUrl":"https://crests.football-data.org/64.png"},"playedGames":38,"won":20,"draw":9,"lost":9,"goalsFor":75,"goalsAgainst":45,"goalDifference":30,"points":69,"form":"LWWDW"},
    {"position":6,"team":{"name":"Brighton","crestUrl":"https://crests.football-data.org/397.png"},"playedGames":38,"won":19,"draw":8,"lost":11,"goalsFor":60,"goalsAgainst":50,"goalDifference":10,"points":65,"form":"WDWLW"},
    {"position":7,"team":{"name":"Aston Villa","crestUrl":"https://crests.football-data.org/58.png"},"playedGames":38,"won":18,"draw":10,"lost":10,"goalsFor":58,"goalsAgainst":48,"goalDifference":10,"points":64,"form":"WLDWW"},
    {"position":8,"team":{"name":"Tottenham Hotspur","crestUrl":"https://crests.football-data.org/73.png"},"playedGames":38,"won":17,"draw":9,"lost":12,"goalsFor":55,"goalsAgainst":45,"goalDifference":10,"points":60,"form":"DWLWD"},
    {"position":9,"team":{"name":"Brentford","crestUrl":"https://crests.football-data.org/397.png"},"playedGames":38,"won":16,"draw":8,"lost":14,"goalsFor":50,"goalsAgainst":45,"goalDifference":5,"points":56,"form":"WLWDL"},
    {"position":10,"team":{"name":"Fulham","crestUrl":"https://crests.football-data.org/572.png"},"playedGames":38,"won":15,"draw":10,"lost":13,"goalsFor":52,"goalsAgainst":50,"goalDifference":2,"points":55,"form":"DWLWD"},
    {"position":11,"team":{"name":"Chelsea","crestUrl":"https://crests.football-data.org/61.png"},"playedGames":38,"won":14,"draw":11,"lost":13,"goalsFor":48,"goalsAgainst":45,"goalDifference":3,"points":53,"form":"LWDWL"},
    {"position":12,"team":{"name":"Crystal Palace","crestUrl":"https://crests.football-data.org/354.png"},"playedGames":38,"won":13,"draw":12,"lost":13,"goalsFor":45,"goalsAgainst":50,"goalDifference":-5,"points":51,"form":"DLWDW"},
    {"position":13,"team":{"name":"Everton","crestUrl":"https://crests.football-data.org/62.png"},"playedGames":38,"won":12,"draw":13,"lost":13,"goalsFor":44,"goalsAgainst":48,"goalDifference":-4,"points":49,"form":"WLDLW"},
    {"position":14,"team":{"name":"Leicester City","crestUrl":"https://crests.football-data.org/338.png"},"playedGames":38,"won":12,"draw":12,"lost":14,"goalsFor":46,"goalsAgainst":52,"goalDifference":-6,"points":48,"form":"LWDLD"},
    {"position":15,"team":{"name":"Southampton","crestUrl":"https://crests.football-data.org/340.png"},"playedGames":38,"won":11,"draw":12,"lost":15,"goalsFor":42,"goalsAgainst":55,"goalDifference":-13,"points":45,"form":"LDWLW"},
    {"position":16,"team":{"name":"Wolves","crestUrl":"https://crests.football-data.org/33.png"},"playedGames":38,"won":10,"draw":13,"lost":15,"goalsFor":38,"goalsAgainst":52,"goalDifference":-14,"points":43,"form":"DLWDL"},
    {"position":17,"team":{"name":"Bournemouth","crestUrl":"https://crests.football-data.org/1044.png"},"playedGames":38,"won":9,"draw":12,"lost":17,"goalsFor":40,"goalsAgainst":60,"goalDifference":-20,"points":39,"form":"LDLWL"},
    {"position":18,"team":{"name":"Nottingham Forest","crestUrl":"https://crests.football-data.org/351.png"},"playedGames":38,"won":8,"draw":10,"lost":20,"goalsFor":35,"goalsAgainst":65,"goalDifference":-30,"points":34,"form":"LLDLW"},
    {"position":19,"team":{"name":"Sheffield United","crestUrl":"https://crests.football-data.org/354.png"},"playedGames":38,"won":7,"draw":12,"lost":19,"goalsFor":30,"goalsAgainst":65,"goalDifference":-35,"points":33,"form":"LDLLD"},
    {"position":20,"team":{"name":"Luton Town","crestUrl":"https://crests.football-data.org/354.png"},"playedGames":38,"won":6,"draw":10,"lost":22,"goalsFor":28,"goalsAgainst":70,"goalDifference":-42,"points":28,"form":"LLDLL"}
  ]
}
